<item>
	<title>Walking in Boston</title>
	<link>http://tuttle2texas.posterous.com/walking-in-boston-1</link>
	<pubDate>Thu Mar 04 04:22:00 -0800 2010</pubDate>
	
	<dc:creator><![CDATA[Lloyd Davis]]></dc:creator>
	
	

	<category><![CDATA[Uncategorized]]></category>

	<category domain="category" nicename="uncategorized"><![CDATA[Uncategorized]]></category>

  <guid isPermaLink="false">http://tuttle2texas.posterous.com/walking-in-boston-1</guid>
	<description></description>
	<content:encoded><![CDATA[<p>
<object type="application/x-shockwave-flash" height="129" width="400">
<param name="movie" value="http://boos.audioboo.fm/swf/fullsize_player.swf" />
<param name="scale" value="noscale" />
<param name="salign" value="lt" />
<param name="bgColor" value="#FFFFFF" />
<param name="allowScriptAccess" value="always" />
<param name="wmode" value="window" />
<param name="FlashVars" value="mp3Title=Walking+in+boston&amp;mp3Time=01.26pm+03+Mar+2010&amp;mp3=http%3A%2F%2Faudioboo.fm%2Fboos%2F102164-walking-in-boston.mp3&amp;mp3Author=Lloyddavis&amp;mp3LinkURL=http%3A%2F%2Faudioboo.fm%2Fboos%2F102164-walking-in-boston" /><a href="http://audioboo.fm/boos/102164-walking-in-boston.mp3">Listen!</a>
</object>
<p /></p>
<div>recorded yesterday between my hotel and the <a href="http://techsuperpowers.com/digilounge">digilounge</a></div>]]></content:encoded>
	<excerpt:encoded><![CDATA[Listen! recorded yesterday between my hotel and the digilounge]]></excerpt:encoded>	

	<wp:post_date>Thu Mar 04 04:22:00 -0800 2010</wp:post_date>
	<wp:post_date_gmt>%= display_date %></wp:post_date_gmt>
	<wp:comment_status>open</wp:comment_status>
	<wp:ping_status>open</wp:ping_status>
	<wp:post_name></wp:post_name>
	<wp:status>publish</wp:status>
	<wp:post_parent>0</wp:post_parent>
	<wp:menu_order>0</wp:menu_order>
	<wp:post_type>post</wp:post_type>
	<wp:post_password></wp:post_password>
	<wp:is_sticky>0</wp:is_sticky>

	
</item>
